wordwiz/__init__.py
wordwiz/core.py
wordwiz/visualize.py
wordwiz-0.1.1.dist-info/licenses/LICENSE.txt
wordwiz-0.1.1.dist-info/METADATA
wordwiz-0.1.1.dist-info/WHEEL
wordwiz-0.1.1.dist-info/top_level.txt
wordwiz-0.1.1.dist-info/RECORD
