Metadata-Version: 2.4
Name: wordwiz
Version: 0.1.1
Summary: A simple Python toolkit for text preprocessing, frequency analysis, and word cloud generation.
Author-email: Dhruv Marwal <dhruvmarwal@gmail.com>
License: MIT
Requires-Python: >=3.8
License-File: LICENSE.txt
Requires-Dist: nltk
Requires-Dist: wordcloud
Requires-Dist: matplotlib
Provides-Extra: dev
Requires-Dist: build; extra == "dev"
Requires-Dist: twine; extra == "dev"
Dynamic: license-file
